notechat/__init__.py
notechat/pd2html.py
notechat/resource/__init__.py
notechat/resource/database.py
notechat/resource/video/__init__.py
notechat-0.1.3.dist-info/METADATA
notechat-0.1.3.dist-info/WHEEL
notechat-0.1.3.dist-info/top_level.txt
notechat-0.1.3.dist-info/RECORD
