Metadata-Version: 2.1
Name: notechat
Version: 0.1.3
Summary: notechat
Home-page: https://github.com/1007530194
Author: niult
Author-email: 1007530194@qq.com
License: UNKNOWN
Platform: UNKNOWN
Requires-Dist: notebuild
Requires-Dist: notedrive
